Metadata-Version: 2.1
Name: tcs-sqlwhat2
Version: 3.8.1
Summary: Submission correctness tests for SQL
Home-page: https://github.com/datacamp/sqlwhat
Author: Michael Chow, Filip Schouwenaars
Author-email: michael@datacamp.com
Maintainer: Jeroen Hermans
Maintainer-email: content-engineering@datacamp.com
License: UNKNOWN
Platform: UNKNOWN
Classifier: Programming Language :: Python :: 3
Classifier: License :: OSI Approved :: GNU Affero General Public License v3
Classifier: Operating System :: OS Independent
License-File: LICENSE
